os_tester/__init__.py
os_tester/debug_plot.py
os_tester/stages.py
os_tester/vm.py
os_tester-1.2.0.dist-info/licenses/LICENSE
os_tester-1.2.0.dist-info/METADATA
os_tester-1.2.0.dist-info/WHEEL
os_tester-1.2.0.dist-info/top_level.txt
os_tester-1.2.0.dist-info/RECORD
