Metadata-Version: 2.4
Name: os-tester
Version: 1.2.0
Summary: A Python pip package to automate testing of whole operating systems with an image recognition based approach and libvirt (qemu). Inspired by openQA.
Author-email: Fabian Sauter <fabian.sauter+pip@apsensing.com>
Maintainer-email: Fabian Sauter <fabian.sauter+pip@apsensing.com>
License: GNU General Public License v3 (GPLv3)
Project-URL: Homepage, https://github.com/AP-Sensing/os-tester
Project-URL: Repository, https://github.com/AP-Sensing/os-tester
Project-URL: Issues, https://github.com/AP-Sensing/os-tester/issues
Keywords: testing,os,qemu,libvirt
Classifier: Programming Language :: Python :: 3 :: Only
Classifier: Programming Language :: Python :: Implementation
Classifier: Operating System :: OS Independent
Classifier: Intended Audience :: Developers
Classifier: License :: OSI Approved :: GNU General Public License v3 (GPLv3)
Classifier: Natural Language :: English
Requires-Python: >=3.7
License-File: LICENSE
Requires-Dist: scikit-image==0.26.0
Requires-Dist: opencv-python-headless
Requires-Dist: libvirt-python
Requires-Dist: PyYAML
Requires-Dist: numpy
Requires-Dist: matplotlib
Dynamic: license-file
